itk_napari_conversion.py
itk_napari_conversion-0.5.1.dist-info/METADATA
itk_napari_conversion-0.5.1.dist-info/WHEEL
itk_napari_conversion-0.5.1.dist-info/licenses/LICENSE
itk_napari_conversion-0.5.1.dist-info/RECORD
