Metadata-Version: 2.4
Name: itk_napari_conversion
Version: 0.5.1
Summary: Convert between itk and napari data structures
Project-URL: Homepage, https://github.com/InsightSoftwareConsortium/itk-napari-conversion
Author-email: Matt McCormick <matt@fideus.io>
License-File: LICENSE
Classifier: Development Status :: 4 - Beta
Classifier: Intended Audience :: Developers
Classifier: Intended Audience :: Education
Classifier: Intended Audience :: Healthcare Industry
Classifier: Intended Audience :: Science/Research
Classifier: License :: OSI Approved :: Apache Software License
Classifier: Programming Language :: Python
Classifier: Topic :: Scientific/Engineering
Classifier: Topic :: Scientific/Engineering :: Information Analysis
Classifier: Topic :: Scientific/Engineering :: Medical Science Apps.
Classifier: Topic :: Software Development :: Libraries
Requires-Python: <3.14,>=3.10
Requires-Dist: itk-core>=5.2.0
Requires-Dist: napari
Provides-Extra: test
Requires-Dist: pytest; extra == 'test'
